[
  {
    "id": "13155465",
    "title": "new juicy 18 yr old teen riley momsen s first fuck/",
    "url": "https://videohotmovs.com/videos/13155465/new-juicy-18-yr-old-teen-riley-momsen-s-first-fuck/?source=1855371379",
    "embedUrl": "https://videohotmovs.com/embed/13155465?source=1855371379",
    "thumb": "https://videohotmovs.com/thumbs/13155465.jpg"
  },
  {
    "id": "13155463",
    "title": "helping hand familydick/",
    "url": "https://videohotmovs.com/videos/13155463/helping-hand-familydick/?source=1855371379",
    "embedUrl": "https://videohotmovs.com/embed/13155463?source=1855371379",
    "thumb": "https://videohotmovs.com/thumbs/13155463.jpg"
  },
  {
    "id": "13155461",
    "title": "venezuelan venus with vibrator/",
    "url": "https://videohotmovs.com/videos/13155461/venezuelan-venus-with-vibrator/?source=1855371379",
    "embedUrl": "https://videohotmovs.com/embed/13155461?source=1855371379",
    "thumb": "https://videohotmovs.com/thumbs/13155461.jpg"
  },
  {
    "id": "13155459",
    "title": "silvia dellai and kristy black fisting each other before hot/",
    "url": "https://videohotmovs.com/videos/13155459/silvia-dellai-and-kristy-black-fisting-each-other-before-hot/?source=1855371379",
    "embedUrl": "https://videohotmovs.com/embed/13155459?source=1855371379",
    "thumb": "https://videohotmovs.com/thumbs/13155459.jpg"
  },
  {
    "id": "13155457",
    "title": "madison kallie taylor in kallie wanna ride teenfidelity/",
    "url": "https://videohotmovs.com/videos/13155457/madison-kallie-taylor-in-kallie-wanna-ride-teenfidelity/?source=1855371379",
    "embedUrl": "https://videohotmovs.com/embed/13155457?source=1855371379",
    "thumb": "https://videohotmovs.com/thumbs/13155457.jpg"
  },
  {
    "id": "13155455",
    "title": "cam model anissa kate records office dp gangbang for fans/",
    "url": "https://videohotmovs.com/videos/13155455/cam-model-anissa-kate-records-office-dp-gangbang-for-fans/?source=1855371379",
    "embedUrl": "https://videohotmovs.com/embed/13155455?source=1855371379",
    "thumb": "https://videohotmovs.com/thumbs/13155455.jpg"
  },
  {
    "id": "13155453",
    "title": "tifanny fox asshole video sz63/",
    "url": "https://videohotmovs.com/videos/13155453/tifanny-fox-asshole-video-sz63/?source=1855371379",
    "embedUrl": "https://videohotmovs.com/embed/13155453?source=1855371379",
    "thumb": "https://videohotmovs.com/thumbs/13155453.jpg"
  },
  {
    "id": "13155451",
    "title": "black meat jada sparks 2on1 bbc atm balls deep anal dp/",
    "url": "https://videohotmovs.com/videos/13155451/black-meat-jada-sparks-2on1-bbc-atm-balls-deep-anal-dp/?source=1855371379",
    "embedUrl": "https://videohotmovs.com/embed/13155451?source=1855371379",
    "thumb": "https://videohotmovs.com/thumbs/13155451.jpg"
  },
  {
    "id": "13155447",
    "title": "fantastic asian girl squirts and gets fucked and toyed/",
    "url": "https://videohotmovs.com/videos/13155447/fantastic-asian-girl-squirts-and-gets-fucked-and-toyed/?source=1855371379",
    "embedUrl": "https://videohotmovs.com/embed/13155447?source=1855371379",
    "thumb": "https://videohotmovs.com/thumbs/13155447.jpg"
  },
  {
    "id": "13155445",
    "title": "dan fucks cherry and eliza in a crazy threesome/",
    "url": "https://videohotmovs.com/videos/13155445/dan-fucks-cherry-and-eliza-in-a-crazy-threesome/?source=1855371379",
    "embedUrl": "https://videohotmovs.com/embed/13155445?source=1855371379",
    "thumb": "https://videohotmovs.com/thumbs/13155445.jpg"
  },
  {
    "id": "13155443",
    "title": "how do you sleep dadcreep/",
    "url": "https://videohotmovs.com/videos/13155443/how-do-you-sleep-dadcreep/?source=1855371379",
    "embedUrl": "https://videohotmovs.com/embed/13155443?source=1855371379",
    "thumb": "https://videohotmovs.com/thumbs/13155443.jpg"
  }]